Workbook

Sheet Instructions for Use
B2: ISO/IEC 27001:2022 Gap analysis questionnaire - Instructions for use - Falcon Freight Solutions
B4: This questionnaire provides a structured framework for systematically evaluating an organization's information security management practices against ISO/IEC 27001:2022. While it can be used for self-assessment, it is primarily designed to support a gap analysis facilitated by an experienced ISO27k consultant or auditor offering guidance, clarification and a more objective assessment. The questionnaire has two parts: Part 1 - ISO/IEC 27001:2022 Clauses (28 questions) - covers the ISO/IEC 27001:2022 main body clauses 4 to 10. Conformity with the requirements in these clauses is mandatory for all certified organizations. Part 2 - ISO/IEC 27001:2022 Annex A information security controls (133 questions) - covers the ISO/IEC 27001:2022 Annex A controls. Conformity with the requirements in the Annex is discretionary: it is only required if the organization determines that the controls are applicable, meaming that they are required to mitigate the associated information risks. Understanding the questions To better understand the requirements behind each question: Part 1 - ISO/IEC 27001:2022 Clauses - Please study ISO/IEC 27001:2022 Clauses 4 to 10. Part 2 - ISO/IEC 27001:2022 Annex A Controls - Please study the 'Guidance' paragraphs for each control in ISO/IEC 27002:2022. ISO/IEC 27002 provides about a page of explanation for each control, expanding on the control names given in ISO/IEC 27001 Annex A. Answering questions When answering, please use the dropdown box to select your response. In the 'Policy' or 'other document(s)' cells, please provide details of any documentation supporting your response, along with the details of the document owner. Any supporting comments would also be helpful. If you reply 'No' or 'Not Applicable' to any question, please explain why, within the context of your organization, the requirement or control is not required and not implemented. Clarification If you need clarification on any questions, please select 'Clarification required' from the dropdown box and ask for clarification next to the blue highlighted question number in the Clarification worksheet. (Rows in the Clarification worksheet are highlighted automatically when you select 'Clarification required' in the ISO27k Gap Analysis Questions worksheet). Summary of Responses The 'Summary of Responses' tab provides a breakdown of your responses to the gap analysis questionnaire. Gap analysis report Once all responses and evidence have been reviewed and any clarification questions have been answered and accepted, a consolidated gap analysis report will be provided. This report will highlight any identified gaps. It will also make recommendations for improvement as part of the ISO/IEC 27001:2022 certification process. Further details about are provided in the body of the Gap Analysis report. [This gap analysis questionnaire was generously donated to the ISO27k Toolkit by Marty Carter.]
B11: This work is copyright © 2024, Marty Carter and ISO27k Forum, some rights reserved. It is licensed under the Creative Commons Attribution-Noncommercial-Sharealike 4.0 International License. You are welcome to reproduce, circulate, use and create derivative works from this provided that (a) it is not sold or incorporated into a commercial product, (b) it is properly attributed to the ISO27k Forum (www.ISO27001security.com), and (c) if shared, derivative works are shared under the same terms as this.

Sheet Summary of Responses
B2: ISO/IEC 27001:2022 Gap analysis questionnaire - Summary of responses - Falcon Freight Solutions
B4: This table summarises the responses across the two parts of the gap analysis, and is provided as a guide only.
D6: Yes | E6: No | F6: Not Applicable | G6: Refer to comments | H6: Clarification required
B7: ISO/IEC 27001:2022 Clauses (28 questions) | D7: =COUNTIF('ISO27k Gap Analysis Questions'!I10:I43, "1") -> 0 | E7: =COUNTIF('ISO27k Gap Analysis Questions'!J10:J43, "1") -> 22 | F7: =COUNTIF('ISO27k Gap Analysis Questions'!K10:K43, "1") -> 0 | G7: =COUNTIF('ISO27k Gap Analysis Questions'!L10:L43, "1") -> 6 | H7: =COUNTIF('ISO27k Gap Analysis Questions'!M10:M43, "1") -> 0
B8: ISO/IEC 27001:2022 Annex A Controls (133 questions)
B9: Domain 5 - Organizational Controls (66 questions) | D9: =COUNTIF('ISO27k Gap Analysis Questions'!I46:I111, "1") -> 2 | E9: =COUNTIF('ISO27k Gap Analysis Questions'!J46:J111, "1") -> 51 | F9: =COUNTIF('ISO27k Gap Analysis Questions'!K46:K111, "1") -> 0 | G9: =COUNTIF('ISO27k Gap Analysis Questions'!L46:L111, "1") -> 13 | H9: =COUNTIF('ISO27k Gap Analysis Questions'!M46:M111, "1") -> 0
B10: Domain 6 - People Controls (15 questions) | D10: =COUNTIF('ISO27k Gap Analysis Questions'!I113:I127, "1") -> 5 | E10: =COUNTIF('ISO27k Gap Analysis Questions'!J113:J127, "1") -> 6 | F10: =COUNTIF('ISO27k Gap Analysis Questions'!K113:K127, "1") -> 0 | G10: =COUNTIF('ISO27k Gap Analysis Questions'!L113:L127, "1") -> 4 | H10: =COUNTIF('ISO27k Gap Analysis Questions'!M113:M127, "1") -> 0
B11: Domain 7 - Physical Controls (14 questions) | D11: =COUNTIF('ISO27k Gap Analysis Questions'!I129:I142, "1") -> 7 | E11: =COUNTIF('ISO27k Gap Analysis Questions'!J129:J142, "1") -> 3 | F11: =COUNTIF('ISO27k Gap Analysis Questions'!K129:K142, "1") -> 0 | G11: =COUNTIF('ISO27k Gap Analysis Questions'!L129:L142, "1") -> 4 | H11: =COUNTIF('ISO27k Gap Analysis Questions'!M129:M142, "1") -> 0
B12: Domain 8 - Technological Controls (38 questions) | D12: =COUNTIF('ISO27k Gap Analysis Questions'!I144:I181, "1") -> 2 | E12: =COUNTIF('ISO27k Gap Analysis Questions'!J144:J181, "1") -> 18 | F12: =COUNTIF('ISO27k Gap Analysis Questions'!K144:K181, "1") -> 9 | G12: =COUNTIF('ISO27k Gap Analysis Questions'!L144:L181, "1") -> 9 | H12: =COUNTIF('ISO27k Gap Analysis Questions'!M144:M181, "1") -> 0
C14: Total number of clarification questions asked
B15: This box below serves as a simple check for how many questions require clarification from the table above against how many questions were actually asked in the Clarification worksheet. The two totals should match.
B17: ISO/IEC 27001:2022 Clauses (28 questions) | D17: =COUNTIF(Clarification!F6:F39, "1") -> 0 | E17: =IF(AND(H7>0,D17<H7),"You have requested clarification on ISO/IEC 27001 Clause questions but have not yet entered them all in the Clarification worksheet.","")
B18: ISO/IEC 27001:2022 Annex A security controls (133 questions)
B19: Domain 5 - Organizational Controls (66 questions) | D19: =COUNTIF(Clarification!F42:F107, "1") -> 0 | E19: =IF(AND(H9>0,D19<H9),"You have requested clarification on ISO/IEC 27001 Organizational Control questions but have not yet entered them all in the Clarification worksheet.","")
B20: Domain 6 - People Controls (15 questions) | D20: =COUNTIF(Clarification!F109:F123, "1") -> 0 | E20: =IF(AND(H10>0,D20<H10),"You have requested clarification on ISO/IEC 27001 People Control questions but have not yet entered them all in the Clarification worksheet.","")
B21: Domain 7 - Physical Controls (14 questions) | D21: =COUNTIF(Clarification!F125:F138, "1") -> 0 | E21: =IF(AND(H11>0,D21<H11),"You have requested clarification on ISO/IEC 27001 Physical Control questions but have not yet entered them all in the Clarification worksheet.","")
B22: Domain 8 - Technological Controls (38 questions) | D22: =COUNTIF(Clarification!F140:F177, "1") -> 0 | E22: =IF(AND(H12>0,D22<H12),"You have requested clarification on ISO/IEC 27001 Technological Control questions but have not yet entered them all in the Clarification worksheet.","")
E24: The cells above contain formulae and should not be deleted.

Sheet ISO27k Gap Analysis Questions
B1: ISO/IEC 27001:2022 Information Security Management System (ISMS) GAP ANALYSIS QUESTIONNAIRE Falcon Freight Solutions
B3: ="There are "&COUNT(A10:A43)&" ISO/IEC 27001:2022 Clauses questions, plus "&COUNT(A46:A181)&" ISO/IEC 27001:2022 Annex A questions across the 4 security control domains. So far, you've answered "&COUNTIF(I10:I43,"1")&" ISO/IEC 27001:2022 Clause questions as Yes, "&COUNTIF(J10:J43,"1")&" as No, "&COUNTIF(K10:K43,"1")&" as Not Applicable, referred "&COUNTIF(L10:L43,"1")&" question(s) to comments, and asked for clarification on "&COUNTIF(M10:M43,"1")&" question(s). So far, you've answered "&COUNTIF(I46:I181,"1")&" ISO/IEC 27001:2022 Annex A questions as Yes, "&COUNTIF(J46:J181,"1")&" as No, "&COUNTIF(K46:K181,"1")&" as Not Applicable, referred "&COUNTIF(L46:L181,"1")&" question(s) to comments, and asked for clarification on "&COUNTIF(M46:M181,"1")&" question(s)." -> There are 28 ISO/IEC 27001:2022 Clauses questions, plus 133 ISO/IEC 27001:2022 Annex A questions across the 4 security control domains. So far, you've answered 0 ISO/IEC 27001:2022 Clause questions as Yes, 22 as No, 0 as Not Applicable, referred 6 question(s) to comments, and asked for clarification on 0 question(s). So far, you've answered 16 ISO/IEC 27001:2022 Annex A questions as Yes, 78 as No, 9 as Not Applicable, referred 30 question(s) to comments, and asked for clarification on 0 question(s).
B5: ISO/IEC 27001:2022 Clauses gap analysis questionnaire | D5: ISO/IEC 27001:2022 Annex A security controls gap analysis questionnaire
B7: Ref | C7: Question | D7: Response | E7: Policy | F7: Other document | G7: Document reference | H7: Comments | I7: These columns can be hidden
B8: ISO/IEC 27001:2022 Clauses gap analysis questionnaire
B9: Clause 4 - Context of the Organization | D9: Select your response from the dropdown box. | E9: Enter the details of the Policy related to this requirement (if applicable) | F9: Enter the details of the any other document related to this requirement (if applicable) | G9: Enter the document(s) reference details or a link to the document | H9: Add comments or enter a customised response here. | I9: Yes | J9: No | K9: NA | L9: Refer to comments | M9: Clarification required
A10: 1 | B10: 4.1a | C10: Has the organization determined external and internal issues that are relevant to and affect the ISMS' ability to achieve its intended outcomes? | D10: No | H10: External/internal issues (regional regulatory landscape, competitor and vendor dependencies) are discussed informally at leadership meetings but not formally documented as ISMS context. | I10: =IF($D10="Yes", 1, "") | J10: =IF($D10="No", 1, "") -> 1 | K10: =IF($D10="Not Applicable", 1, "") | L10: =IF($D10="Refer to comments", 1, "") | M10: =IF($D10="Clarification required", 1, "")
A11: 1 | B11: 4.2a | C11: Has the organization identified interested parties relevant to the ISMS, their relevant requirements and which of these will be addressed by the ISMS? | D11: No | H11: Interested parties (customers, customs authorities, freight partners, regulators) are not formally identified or mapped against ISMS requirements. | I11: =IF($D11="Yes", 1, "") | J11: =IF($D11="No", 1, "") -> 1 | K11: =IF($D11="Not Applicable", 1, "") | L11: =IF($D11="Refer to comments", 1, "") | M11: =IF($D11="Clarification required", 1, "")
A12: 1 | B12: 4.3a | C12: Has the organization determined the scope of its ISMS? | D12: No | H12: No ISMS scope has been defined; Falcon Freight has not yet formalized which sites, systems or business units would be in scope. | I12: =IF($D12="Yes", 1, "") | J12: =IF($D12="No", 1, "") -> 1 | K12: =IF($D12="Not Applicable", 1, "") | L12: =IF($D12="Refer to comments", 1, "") | M12: =IF($D12="Clarification required", 1, "")
A13: 1 | B13: 4.4a | C13: Has the organization established, implemented, maintained, and continually improves an ISMS in accordance with the requirements of ISO/IEC 27001:2022? | D13: No | H13: No ISMS has been established; information security is currently managed on an ad hoc basis by the IT team. | I13: =IF($D13="Yes", 1, "") | J13: =IF($D13="No", 1, "") -> 1 | K13: =IF($D13="Not Applicable", 1, "") | L13: =IF($D13="Refer to comments", 1, "") | M13: =IF($D13="Clarification required", 1, "")
B14: Clause 5 - Leadership | D14: Select your response from the dropdown box. | E14: Enter the details of the Policy related to this requirement (if applicable) | F14: Enter the details of the any other document related to this requirement (if applicable) | G14: Enter the document(s) reference details or a link to the document | H14: Add comments or enter a customised response here. | I14: Yes | J14: No | K14: NA | L14: Refer to comments | M14: Clarification required
A15: 1 | B15: 5.1a | C15: Are the objectives of the ISMS compatible with the organization's strategic direction and mission? | D15: Refer to comments | H15: Management supports growth and client trust generally, but no documented ISMS objectives exist to compare against strategic direction. | I15: =IF($D15="Yes", 1, "") | J15: =IF($D15="No", 1, "") | K15: =IF($D15="Not Applicable", 1, "") | L15: =IF($D15="Refer to comments", 1, "") -> 1 | M15: =IF($D15="Clarification required", 1, "")
A16: 1 | B16: 5.2a | C16: Is an Information Security Policy available and appropriate to the purpose and context of the organization and does it support the strategic direction of the company? | D16: No | H16: No formal Information Security Policy exists; IT operates from informal practices rather than an approved policy document. | I16: =IF($D16="Yes", 1, "") | J16: =IF($D16="No", 1, "") -> 1 | K16: =IF($D16="Not Applicable", 1, "") | L16: =IF($D16="Refer to comments", 1, "") | M16: =IF($D16="Clarification required", 1, "")
A17: 1 | B17: 5.3a | C17: Has the organization's top management established (and are they supportive of,) a mechanism for communicating responsibilities and authorities for roles relevant to information security within the organization? | D17: Refer to comments | H17: Responsibilities are communicated verbally by the IT Manager and Operations leads across regional offices, but no formal RACI or communication mechanism is documented. | I17: =IF($D17="Yes", 1, "") | J17: =IF($D17="No", 1, "") | K17: =IF($D17="Not Applicable", 1, "") | L17: =IF($D17="Refer to comments", 1, "") -> 1 | M17: =IF($D17="Clarification required", 1, "")
B18: Clause 6 - Planning | D18: Select your response from the dropdown box. | E18: Enter the details of the Policy related to this requirement (if applicable) | F18: Enter the details of the any other document related to this requirement (if applicable) | G18: Enter the document(s) reference details or a link to the document | H18: Add comments or enter a customised response here. | I18: Yes | J18: No | K18: NA | L18: Refer to comments | M18: Clarification required
A19: 1 | B19: 6.1a | C19: Has organization defined and applied an information security risk assessment process? | D19: No | H19: No formal information security risk assessment methodology has been defined or applied across the organization. | I19: =IF($D19="Yes", 1, "") | J19: =IF($D19="No", 1, "") -> 1 | K19: =IF($D19="Not Applicable", 1, "") | L19: =IF($D19="Refer to comments", 1, "") | M19: =IF($D19="Clarification required", 1, "")
A20: 1 | B20: 6.1b | C20: Does the organization have a documented risk treatment process? | D20: No | H20: No documented risk treatment process exists; risks are addressed reactively when incidents occur. | I20: =IF($D20="Yes", 1, "") | J20: =IF($D20="No", 1, "") -> 1 | K20: =IF($D20="Not Applicable", 1, "") | L20: =IF($D20="Refer to comments", 1, "") | M20: =IF($D20="Clarification required", 1, "")
A21: 1 | B21: 6.1c | C21: Has the organization produced a Statement of Applicability (SoA)? | D21: No | H21: No Statement of Applicability has been produced. | I21: =IF($D21="Yes", 1, "") | J21: =IF($D21="No", 1, "") -> 1 | K21: =IF($D21="Not Applicable", 1, "") | L21: =IF($D21="Refer to comments", 1, "") | M21: =IF($D21="Clarification required", 1, "")
A22: 1 | B22: 6.2a | C22: Has the organization established information security objectives at applicable functions and levels within the business and are they consistent with the Information Security Policy? | D22: No | H22: No information security objectives have been set at a functional or departmental level. | I22: =IF($D22="Yes", 1, "") | J22: =IF($D22="No", 1, "") -> 1 | K22: =IF($D22="Not Applicable", 1, "") | L22: =IF($D22="Refer to comments", 1, "") | M22: =IF($D22="Clarification required", 1, "")
A23: 1 | B23: 6.3a | C23: When the organization determines the need for changes to the information security management system, are the changes carried out in a planned manner? | D23: Refer to comments | H23: Changes to IT systems (e.g. the shipment tracking platform) go through basic IT change control, but this is not linked to a formal ISMS change process. | I23: =IF($D23="Yes", 1, "") | J23: =IF($D23="No", 1, "") | K23: =IF($D23="Not Applicable", 1, "") | L23: =IF($D23="Refer to comments", 1, "") -> 1 | M23: =IF($D23="Clarification required", 1, "")
B24: Clause 7 - Support | D24: Select your response from the dropdown box. | E24: Enter the details of the Policy related to this requirement (if applicable) | F24: Enter the details of the any other document related to this requirement (if applicable) | G24: Enter the document(s) reference details or a link to the document | H24: Add comments or enter a customised response here. | I24: Yes | J24: No | K24: NA | L24: Refer to comments | M24: Clarification required
A25: 1 | B25: 7.1a | C25: Has the organization determined and does it provide the resources needed for the establishment, implementation, maintenance, and continual improvement of the ISMS? | D25: Refer to comments | H25: The IT department is resourced for day-to-day operations, but no dedicated budget or resourcing has been allocated for ISMS establishment. | I25: =IF($D25="Yes", 1, "") | J25: =IF($D25="No", 1, "") | K25: =IF($D25="Not Applicable", 1, "") | L25: =IF($D25="Refer to comments", 1, "") -> 1 | M25: =IF($D25="Clarification required", 1, "")
A26: 1 | B26: 7.2a | C26: Has the organization determined the necessary competence of person(s) doing work under its control that affects its information security performance? | D26: No | H26: Competence requirements for information-security-relevant roles have not been formally defined. | I26: =IF($D26="Yes", 1, "") | J26: =IF($D26="No", 1, "") -> 1 | K26: =IF($D26="Not Applicable", 1, "") | L26: =IF($D26="Refer to comments", 1, "") | M26: =IF($D26="Clarification required", 1, "")
A27: 1 | B27: 7.3a | C27: Are the organizations employees made aware of the Information Security Policy? | D27: No | H27: Employees are not made aware of an Information Security Policy, as none currently exists. | I27: =IF($D27="Yes", 1, "") | J27: =IF($D27="No", 1, "") -> 1 | K27: =IF($D27="Not Applicable", 1, "") | L27: =IF($D27="Refer to comments", 1, "") | M27: =IF($D27="Clarification required", 1, "")
A28: 1 | B28: 7.4a | C28: Has the organization determined the need for internal and external communications relevant to the ISMS? | D28: Refer to comments | H28: Internal/external communications happen through normal business channels (email, regional office calls) but have not been assessed against ISMS communication needs. | I28: =IF($D28="Yes", 1, "") | J28: =IF($D28="No", 1, "") | K28: =IF($D28="Not Applicable", 1, "") | L28: =IF($D28="Refer to comments", 1, "") -> 1 | M28: =IF($D28="Clarification required", 1, "")
A29: 1 | B29: 7.5a | C29: Does the organization's ISMS include documented information as required by ISO/IEC 27001:2022? | D29: No | H29: No ISMS documented information (policies, procedures, records) is currently maintained. | I29: =IF($D29="Yes", 1, "") | J29: =IF($D29="No", 1, "") -> 1 | K29: =IF($D29="Not Applicable", 1, "") | L29: =IF($D29="Refer to comments", 1, "") | M29: =IF($D29="Clarification required", 1, "")
A30: 1 | B30: 7.5b | C30: Is documented information required by the ISMS and ISO/IEC 27001:2022 controlled? | D30: No | H30: No document control process exists for information-security-related documentation. | I30: =IF($D30="Yes", 1, "") | J30: =IF($D30="No", 1, "") -> 1 | K30: =IF($D30="Not Applicable", 1, "") | L30: =IF($D30="Refer to comments", 1, "") | M30: =IF($D30="Clarification required", 1, "")
B31: Clause 8 - Operation | D31: Select your response from the dropdown box. | E31: Enter the details of the Policy related to this requirement (if applicable) | F31: Enter the details of the any other document related to this requirement (if applicable) | G31: Enter the document(s) reference details or a link to the document | H31: Add comments or enter a customised response here. | I31: Yes | J31: No | K31: NA | L31: Refer to comments | M31: Clarification required
A32: 1 | B32: 8.1a | C32: Has the organization planned, implemented and does it control the processes needed to meet requirements, and to implement the actions determined in Clause 6 (Planning)? | D32: No | H32: No formal operational planning tied to Clause 6 risk treatment exists, since risk treatment itself is not yet formalized. | I32: =IF($D32="Yes", 1, "") | J32: =IF($D32="No", 1, "") -> 1 | K32: =IF($D32="Not Applicable", 1, "") | L32: =IF($D32="Refer to comments", 1, "") | M32: =IF($D32="Clarification required", 1, "")
A33: 1 | B33: 8.2a | C33: Does the organization perform information security risk assessments at planned intervals or when significant changes are proposed or occur? | D33: No | H33: Risk assessments are not performed at planned intervals; reviews only occur reactively after an incident or client audit request. | I33: =IF($D33="Yes", 1, "") | J33: =IF($D33="No", 1, "") -> 1 | K33: =IF($D33="Not Applicable", 1, "") | L33: =IF($D33="Refer to comments", 1, "") | M33: =IF($D33="Clarification required", 1, "")
A34: 1 | B34: 8.3a | C34: Has the organization implemented an information security risk treatment plan? | D34: No | H34: No risk treatment plan has been implemented. | I34: =IF($D34="Yes", 1, "") | J34: =IF($D34="No", 1, "") -> 1 | K34: =IF($D34="Not Applicable", 1, "") | L34: =IF($D34="Refer to comments", 1, "") | M34: =IF($D34="Clarification required", 1, "")
B35: Clause 9 - Performance evaluation | D35: Select your response from the dropdown box. | E35: Enter the details of the Policy related to this requirement (if applicable) | F35: Enter the details of the any other document related to this requirement (if applicable) | G35: Enter the document(s) reference details or a link to the document | H35: Add comments or enter a customised response here. | I35: Yes | J35: No | K35: NA | L35: Refer to comments | M35: Clarification required
A36: 1 | B36: 9.1a | C36: Has the organization determined what needs to monitored and measured, including information security processes and controls? | D36: No | H36: Monitoring is currently limited to basic IT system uptime/performance; no information security monitoring and measurement plan exists. | I36: =IF($D36="Yes", 1, "") | J36: =IF($D36="No", 1, "") -> 1 | K36: =IF($D36="Not Applicable", 1, "") | L36: =IF($D36="Refer to comments", 1, "") | M36: =IF($D36="Clarification required", 1, "")
A37: 1 | B37: 9.2a | C37: Does the organization conduct internal audits of their ISMS at planned intervals? | D37: No | H37: No internal ISMS audit programme exists. | I37: =IF($D37="Yes", 1, "") | J37: =IF($D37="No", 1, "") -> 1 | K37: =IF($D37="Not Applicable", 1, "") | L37: =IF($D37="Refer to comments", 1, "") | M37: =IF($D37="Clarification required", 1, "")
A38: 1 | B38: 9.2b | C38: Has the organization planned, established, implemented and does it maintain an audit programme(s), including the frequency, methods, responsibilities, planning requirements and reporting? | D38: No | H38: No audit programme has been established. | I38: =IF($D38="Yes", 1, "") | J38: =IF($D38="No", 1, "") -> 1 | K38: =IF($D38="Not Applicable", 1, "") | L38: =IF($D38="Refer to comments", 1, "") | M38: =IF($D38="Clarification required", 1, "")
A39: 1 | B39: 9.3a | C39: Does the organizations top management review the organization's ISMS at planned intervals to ensure its continuing suitability, adequacy and effectiveness? | D39: No | H39: Top management does not currently perform structured ISMS management reviews. | I39: =IF($D39="Yes", 1, "") | J39: =IF($D39="No", 1, "") -> 1 | K39: =IF($D39="Not Applicable", 1, "") | L39: =IF($D39="Refer to comments", 1, "") | M39: =IF($D39="Clarification required", 1, "")
A40: 1 | B40: 9.3b | C40: Do the results of management reviews include decisions related to continual improvement opportunities and any needs for changes to the ISMS? | D40: No | H40: As no management review process exists, there are no formal continual improvement decisions being tracked. | I40: =IF($D40="Yes", 1, "") | J40: =IF($D40="No", 1, "") -> 1 | K40: =IF($D40="Not Applicable", 1, "") | L40: =IF($D40="Refer to comments", 1, "") | M40: =IF($D40="Clarification required", 1, "")
B41: Clause 10 - Improvement | D41: Select your response from the dropdown box. | E41: Enter the details of the Policy related to this requirement (if applicable) | F41: Enter the details of the any other document related to this requirement (if applicable) | G41: Enter the document(s) reference details or a link to the document | H41: Add comments or enter a customised response here. | I41: Yes | J41: No | K41: NA | L41: Refer to comments | M41: Clarification required
A42: 1 | B42: 10.1a | C42: Does the organization continually improve the suitability, adequacy, and effectiveness of their ISMS? | D42: No | H42: There is no structured continual improvement process for information security; improvements happen informally when gaps are noticed. | I42: =IF($D42="Yes", 1, "") | J42: =IF($D42="No", 1, "") -> 1 | K42: =IF($D42="Not Applicable", 1, "") | L42: =IF($D42="Refer to comments", 1, "") | M42: =IF($D42="Clarification required", 1, "")
A43: 1 | B43: 10.2a | C43: When a nonconformity occurs, does the organization react to the nonconformity, and as applicable take action to control and correct it? | D43: Refer to comments | H43: Operational nonconformities (e.g. shipment/data handling errors) are corrected on a case-by-case basis but not through a documented ISMS nonconformity process. | I43: =IF($D43="Yes", 1, "") | J43: =IF($D43="No", 1, "") | K43: =IF($D43="Not Applicable", 1, "") | L43: =IF($D43="Refer to comments", 1, "") -> 1 | M43: =IF($D43="Clarification required", 1, "")
B44: ISO/IEC 27001:2022 Annex A security controls gap analysis questionnaire
B45: 5 - ORGANIZATIONAL CONTROLS | D45: Select your response from the dropdown box. | E45: Enter the details of the Policy related to this requirement (if applicable) | F45: Enter the details of the any other document related to this requirement (if applicable) | G45: Enter the document(s) reference details or a link to the document | H45: Add comments or enter a customised response here. | I45: Yes | J45: No | K45: NA | L45: Refer to comments | M45: Clarification required
A46: 1 | B46: 5.1a | C46: Has an Information Security policy and topic-specific policies been defined, approved by management and published? | D46: No | H46: No Information Security policy or topic-specific policies have been defined or published. | I46: =IF($D46="Yes", 1, "") | J46: =IF($D46="No", 1, "") -> 1 | K46: =IF($D46="Not Applicable", 1, "") | L46: =IF($D46="Refer to comments", 1, "") | M46: =IF($D46="Clarification required", 1, "")
A47: 1 | B47: 5.1b | C47: Has the Information Security policy and topic-specific policies been communicated to and acknowledged by relevant personnel and relevant interested parties? | D47: No | H47: As no policy exists, none has been communicated to personnel. | I47: =IF($D47="Yes", 1, "") | J47: =IF($D47="No", 1, "") -> 1 | K47: =IF($D47="Not Applicable", 1, "") | L47: =IF($D47="Refer to comments", 1, "") | M47: =IF($D47="Clarification required", 1, "")
A48: 1 | B48: 5.1c | C48: Are the Information Security policy and topic-specific policies reviewed at planned intervals and if significant changes occur? | D48: No | H48: No policy review cycle is in place. | I48: =IF($D48="Yes", 1, "") | J48: =IF($D48="No", 1, "") -> 1 | K48: =IF($D48="Not Applicable", 1, "") | L48: =IF($D48="Refer to comments", 1, "") | M48: =IF($D48="Clarification required", 1, "")
A49: 1 | B49: 5.2 | C49: Have Information Security roles and responsibilities been defined and allocated according to organizational needs? | D49: Refer to comments | H49: The IT Manager is informally recognized as responsible for security matters, but roles and responsibilities have not been formally defined and allocated. | I49: =IF($D49="Yes", 1, "") | J49: =IF($D49="No", 1, "") | K49: =IF($D49="Not Applicable", 1, "") | L49: =IF($D49="Refer to comments", 1, "") -> 1 | M49: =IF($D49="Clarification required", 1, "")
A50: 1 | B50: 5.3 | C50: Are conflicting duties and conflicting areas of responsibility segregated? | D50: Refer to comments | H50: Segregation of duties is partially achieved by the small size of the IT team, but no formal segregation-of-duties analysis has been performed. | I50: =IF($D50="Yes", 1, "") | J50: =IF($D50="No", 1, "") | K50: =IF($D50="Not Applicable", 1, "") | L50: =IF($D50="Refer to comments", 1, "") -> 1 | M50: =IF($D50="Clarification required", 1, "")
A51: 1 | B51: 5.4 | C51: Does management ensure that all personnel to apply Information Security in accordance with the established Information Security policy, topic-specific policies and procedures of the organization? | D51: No | H51: There is no established policy for personnel to apply, so compliance cannot be enforced. | I51: =IF($D51="Yes", 1, "") | J51: =IF($D51="No", 1, "") -> 1 | K51: =IF($D51="Not Applicable", 1, "") | L51: =IF($D51="Refer to comments", 1, "") | M51: =IF($D51="Clarification required", 1, "")
A52: 1 | B52: 5.5 | C52: Does the organization maintain contact with relevant authorities? | D52: Yes | H52: The compliance team maintains contact with customs authorities and transport regulators across Southern and East Africa as part of normal freight operations. | I52: =IF($D52="Yes", 1, "") -> 1 | J52: =IF($D52="No", 1, "") | K52: =IF($D52="Not Applicable", 1, "") | L52: =IF($D52="Refer to comments", 1, "") | M52: =IF($D52="Clarification required", 1, "")
A53: 1 | B53: 5.6 | C53: Does the organization maintain contact with special interest groups or other specialist security forums and professional associations? | D53: No | H53: The organization does not currently participate in security-focused forums, ISACs or professional security associations. | I53: =IF($D53="Yes", 1, "") | J53: =IF($D53="No", 1, "") -> 1 | K53: =IF($D53="Not Applicable", 1, "") | L53: =IF($D53="Refer to comments", 1, "") | M53: =IF($D53="Clarification required", 1, "")
A54: 1 | B54: 5.7a | C54: Is information relating to information security threats collected and analysed to produce threat intelligence? | D54: No | H54: No threat intelligence collection or analysis capability exists. | I54: =IF($D54="Yes", 1, "") | J54: =IF($D54="No", 1, "") -> 1 | K54: =IF($D54="Not Applicable", 1, "") | L54: =IF($D54="Refer to comments", 1, "") | M54: =IF($D54="Clarification required", 1, "")
A55: 1 | B55: 5.7b | C55: Does the organization categorize threats at the strategic, tactical and operational levels? | D55: No | H55: Threats are not categorized at strategic, tactical or operational levels. | I55: =IF($D55="Yes", 1, "") | J55: =IF($D55="No", 1, "") -> 1 | K55: =IF($D55="Not Applicable", 1, "") | L55: =IF($D55="Refer to comments", 1, "") | M55: =IF($D55="Clarification required", 1, "")
A56: 1 | B56: 5.7c | C56: Does the organization share threat intelligence with other organizations on a mutual basis in order to improve overall threat intelligence? | D56: No | H56: No threat intelligence sharing arrangements exist with other organizations. | I56: =IF($D56="Yes", 1, "") | J56: =IF($D56="No", 1, "") -> 1 | K56: =IF($D56="Not Applicable", 1, "") | L56: =IF($D56="Refer to comments", 1, "") | M56: =IF($D56="Clarification required", 1, "")
A57: 1 | B57: 5.8a | C57: Does the organization integrate information security into project management? | D57: No | H57: Information security is not currently integrated into the project management methodology used for regional expansion and system rollout projects. | I57: =IF($D57="Yes", 1, "") | J57: =IF($D57="No", 1, "") -> 1 | K57: =IF($D57="Not Applicable", 1, "") | L57: =IF($D57="Refer to comments", 1, "") | M57: =IF($D57="Clarification required", 1, "")
A58: 1 | B58: 5.8b | C58: Are information security risks assessed and treated at an early stage and periodically as part of project risks throughout the project life cycle? | D58: No | H58: Information security risks are not assessed as part of project risk management. | I58: =IF($D58="Yes", 1, "") | J58: =IF($D58="No", 1, "") -> 1 | K58: =IF($D58="Not Applicable", 1, "") | L58: =IF($D58="Refer to comments", 1, "") | M58: =IF($D58="Clarification required", 1, "")
A59: 1 | B59: 5.8c | C59: Are information security requirements determined for all types of projects? | D59: No | H59: Information security requirements are not routinely determined for new projects (e.g. new warehouse or regional office rollouts). | I59: =IF($D59="Yes", 1, "") | J59: =IF($D59="No", 1, "") -> 1 | K59: =IF($D59="Not Applicable", 1, "") | L59: =IF($D59="Refer to comments", 1, "") | M59: =IF($D59="Clarification required", 1, "")
A60: 1 | B60: 5.9a | C60: Has an inventory of information and other associated assets, including owners, been developed and maintained? | D60: Refer to comments | H60: IT maintains an informal spreadsheet of hardware and key systems, but this does not constitute a maintained, owner-assigned asset inventory. | I60: =IF($D60="Yes", 1, "") | J60: =IF($D60="No", 1, "") | K60: =IF($D60="Not Applicable", 1, "") | L60: =IF($D60="Refer to comments", 1, "") -> 1 | M60: =IF($D60="Clarification required", 1, "")
A61: 1 | B61: 5.9b | C61: Is the inventory of information and other associated assets accurate, up to date, consistent and aligned with other inventories? | D61: No | H61: The existing asset list is not regularly reconciled or kept up to date. | I61: =IF($D61="Yes", 1, "") | J61: =IF($D61="No", 1, "") -> 1 | K61: =IF($D61="Not Applicable", 1, "") | L61: =IF($D61="Refer to comments", 1, "") | M61: =IF($D61="Clarification required", 1, "")
A62: 1 | B62: 5.9c | C62: Is the location of assets included in the inventory? | D62: Refer to comments | H62: Physical asset locations (warehouses, regional offices) are generally known but not systematically recorded in an inventory. | I62: =IF($D62="Yes", 1, "") | J62: =IF($D62="No", 1, "") | K62: =IF($D62="Not Applicable", 1, "") | L62: =IF($D62="Refer to comments", 1, "") -> 1 | M62: =IF($D62="Clarification required", 1, "")
A63: 1 | B63: 5.9d | C63: Are assets classified in accordance with the organizations classification scheme? | D63: No | H63: No information classification scheme currently exists to classify assets against. | I63: =IF($D63="Yes", 1, "") | J63: =IF($D63="No", 1, "") -> 1 | K63: =IF($D63="Not Applicable", 1, "") | L63: =IF($D63="Refer to comments", 1, "") | M63: =IF($D63="Clarification required", 1, "")
A64: 1 | B64: 5.9e | C64: Is ownership of assets assigned when the assets are created or when assets are transferred? | D64: Refer to comments | H64: New equipment is generally assigned to a department or site informally, without a formal ownership assignment process. | I64: =IF($D64="Yes", 1, "") | J64: =IF($D64="No", 1, "") | K64: =IF($D64="Not Applicable", 1, "") | L64: =IF($D64="Refer to comments", 1, "") -> 1 | M64: =IF($D64="Clarification required", 1, "")
A65: 1 | B65: 5.9f | C65: Is asset ownership reassigned when asset owners leave or change job roles? | D65: No | H65: Asset ownership is not formally reassigned when staff change roles or leave. | I65: =IF($D65="Yes", 1, "") | J65: =IF($D65="No", 1, "") -> 1 | K65: =IF($D65="Not Applicable", 1, "") | L65: =IF($D65="Refer to comments", 1, "") | M65: =IF($D65="Clarification required", 1, "")
... A80: 1 | B80: 5.15b | C80: Has the organization established and implemented a topic specific policy for access control? | D80: No | H80: No topic-specific access control policy has been established. | I80: =IF($D80="Yes", 1, "") | J80: =IF($D80="No", 1, "") -> 1 | K80: =IF($D80="Not Applicable", 1, "") | L80: =IF($D80="Refer to comments", 1, "") | M80: =IF($D80="Clarification required", 1, "")
A81: 1 | B81: 5.16 | C81: Does the organization manage the full life cycle of identities? | D81: Refer to comments | H81: User accounts are created and disabled by IT on request, but there is no formal identity lifecycle management process covering joiners, movers and leavers across regional offices. | I81: =IF($D81="Yes", 1, "") | J81: =IF($D81="No", 1, "") | K81: =IF($D81="Not Applicable", 1, "") | L81: =IF($D81="Refer to comments", 1, "") -> 1 | M81: =IF($D81="Clarification required", 1, "")
A82: 1 | B82: 5.17a | C82: Is the allocation and management of authentication information controlled by a management process? | D82: No | H82: No formal process governs the allocation and management of authentication information (passwords, tokens). | I82: =IF($D82="Yes", 1, "") | J82: =IF($D82="No", 1, "") -> 1 | K82: =IF($D82="Not Applicable", 1, "") | L82: =IF($D82="Refer to comments", 1, "") | M82: =IF($D82="Clarification required", 1, "")
A83: 1 | B83: 5.17b | C83: Does the allocation and management of authentication information include advising personnel on the appropriate handling of authentication information? | D83: No | H83: Personnel are not formally advised on handling of authentication information beyond informal IT guidance. | I83: =IF($D83="Yes", 1, "") | J83: =IF($D83="No", 1, "") -> 1 | K83: =IF($D83="Not Applicable", 1, "") | L83: =IF($D83="Refer to comments", 1, "") | M83: =IF($D83="Clarification required", 1, "")
A84: 1 | B84: 5.17c | C84: Are personnel who have access to or use authentication advised on their responsibilities? | D84: No | H84: No formal communication of authentication responsibilities to personnel exists. | I84: =IF($D84="Yes", 1, "") | J84: =IF($D84="No", 1, "") -> 1 | K84: =IF($D84="Not Applicable", 1, "") | L84: =IF($D84="Refer to comments", 1, "") | M84: =IF($D84="Clarification required", 1, "")
A85: 1 | B85: 5.17d | C85: Does the organization have a password management system in place? | D85: Refer to comments | H85: The cloud shipment tracking platform enforces basic password rules, but there is no organization-wide password management policy covering the on-premise WMS and other systems. | I85: =IF($D85="Yes", 1, "") | J85: =IF($D85="No", 1, "") | K85: =IF($D85="Not Applicable", 1, "") | L85: =IF($D85="Refer to comments", 1, "") -> 1 | M85: =IF($D85="Clarification required", 1, "")
A86: 1 | B86: 5.18a | C86: Are access rights to information and other associated assets provisioned, reviewed, modified and removed in accordance with the organization’s topic-specific policy on and rules for access control? | D86: No | H86: Access rights are not reviewed, modified or removed against a documented access control policy - access changes are handled informally by IT on request. | I86: =IF($D86="Yes", 1, "") | J86: =IF($D86="No", 1, "") -> 1 | K86: =IF($D86="Not Applicable", 1, "") | L86: =IF($D86="Refer to comments", 1, "") | M86: =IF($D86="Clarification required", 1, "")
A87: 1 | B87: 5.18b | C87: Does the organization have a process for the review of access rights? | D87: No | H87: No periodic access rights review process exists. | I87: =IF($D87="Yes", 1, "") | J87: =IF($D87="No", 1, "") -> 1 | K87: =IF($D87="Not Applicable", 1, "") | L87: =IF($D87="Refer to comments", 1, "") | M87: =IF($D87="Clarification required", 1, "")
A88: 1 | B88: 5.19 | C88: Have processes and procedures been defined and implemented to manage the information security risks associated with the use of supplier’s products or services? | D88: No | H88: No formal process exists to manage information security risk from supplier products or services; vendor onboarding does not currently include a security risk assessment. | I88: =IF($D88="Yes", 1, "") | J88: =IF($D88="No", 1, "") -> 1 | K88: =IF($D88="Not Applicable", 1, "") | L88: =IF($D88="Refer to comments", 1, "") | M88: =IF($D88="Clarification required", 1, "")
A89: 1 | B89: 5.2 | C89: Have the relevant information security requirements been established and agreed with each supplier based on the type of supplier relationship? | D89: No | H89: Information security requirements are not consistently agreed with customs brokers, delivery contractors and other suppliers. | I89: =IF($D89="Yes", 1, "") | J89: =IF($D89="No", 1, "") -> 1 | K89: =IF($D89="Not Applicable", 1, "") | L89: =IF($D89="Refer to comments", 1, "") | M89: =IF($D89="Clarification required", 1, "")
A90: 1 | B90: 5.21 | C90: Have processes and procedures been defined and implemented to manage the information security risks associated with the ICT products and services supply chain? | D90: No | H90: No process exists to manage ICT supply chain security risk, including the vendors supporting the cloud tracking platform. | I90: =IF($D90="Yes", 1, "") | J90: =IF($D90="No", 1, "") -> 1 | K90: =IF($D90="Not Applicable", 1, "") | L90: =IF($D90="Refer to comments", 1, "") | M90: =IF($D90="Clarification required", 1, "")
A91: 1 | B91: 5.22 | C91: Does the organization regularly monitor, review, evaluate and manage change in supplier information security practices and service delivery? | D91: No | H91: Supplier security practices and service delivery are not regularly monitored or reviewed. | I91: =IF($D91="Yes", 1, "") | J91: =IF($D91="No", 1, "") -> 1 | K91: =IF($D91="Not Applicable", 1, "") | L91: =IF($D91="Refer to comments", 1, "") | M91: =IF($D91="Clarification required", 1, "")
A92: 1 | B92: 5.23a | C92: Have processes for acquisition, use, management and exit from cloud services been established in accordance with the organization’s information security requirements? | D92: Refer to comments | H92: The cloud shipment tracking platform was selected based on functional and cost criteria; a formal process for acquisition, use, management and exit from cloud services has not been established. | I92: =IF($D92="Yes", 1, "") | J92: =IF($D92="No", 1, "") | K92: =IF($D92="Not Applicable", 1, "") | L92: =IF($D92="Refer to comments", 1, "") -> 1 | M92: =IF($D92="Clarification required", 1, "")
A93: 1 | B93: 5.23b | C93: Has the organization established and communicated topic-specific policy on the use of cloud services to all relevant interested parties? | D93: No | H93: No topic-specific cloud services policy exists. | I93: =IF($D93="Yes", 1, "") | J93: =IF($D93="No", 1, "") -> 1 | K93: =IF($D93="Not Applicable", 1, "") | L93: =IF($D93="Refer to comments", 1, "") | M93: =IF($D93="Clarification required", 1, "")
A94: 1 | B94: 5.24a | C94: Has the organization established appropriate information security incident management processes? | D94: No | H94: No formal information security incident management process has been established; IT responds to issues informally as they arise. | I94: =IF($D94="Yes", 1, "") | J94: =IF($D94="No", 1, "") -> 1 | K94: =IF($D94="Not Applicable", 1, "") | L94: =IF($D94="Refer to comments", 1, "") | M94: =IF($D94="Clarification required", 1, "")
A95: 1 | B95: 5.24b | C95: Has the organization defined roles and responsibilities for the information security incident management process? | D95: No | H95: No roles and responsibilities have been defined for incident management. | I95: =IF($D95="Yes", 1, "") | J95: =IF($D95="No", 1, "") -> 1 | K95: =IF($D95="Not Applicable", 1, "") | L95: =IF($D95="Refer to comments", 1, "") | M95: =IF($D95="Clarification required", 1, "")
A96: 1 | B96: 5.25 | C96: Does the organization have a categorization and prioritization scheme of information security incidents? | D96: No | H96: No categorization or prioritization scheme for security incidents exists. | I96: =IF($D96="Yes", 1, "") | J96: =IF($D96="No", 1, "") -> 1 | K96: =IF($D96="Not Applicable", 1, "") | L96: =IF($D96="Refer to comments", 1, "") | M96: =IF($D96="Clarification required", 1, "")
A97: 1 | B97: 5.26 | C97: Are information security incidents responded to in accordance with documented procedures? | D97: No | H97: There are no documented incident response procedures to follow. | I97: =IF($D97="Yes", 1, "") | J97: =IF($D97="No", 1, "") -> 1 | K97: =IF($D97="Not Applicable", 1, "") | L97: =IF($D97="Refer to comments", 1, "") | M97: =IF($D97="Clarification required", 1, "")
A98: 1 | B98: 5.27 | C98: Has the organization established procedures to quantify and monitor the types, volumes and costs of information security incidents? | D98: No | H98: The organization does not currently track the type, volume or cost of information security incidents. | I98: =IF($D98="Yes", 1, "") | J98: =IF($D98="No", 1, "") -> 1 | K98: =IF($D98="Not Applicable", 1, "") | L98: =IF($D98="Refer to comments", 1, "") | M98: =IF($D98="Clarification required", 1, "")
A99: 1 | B99: 5.28 | C99: Has the organization established and implemented procedures for the identification, collection, acquisition and preservation of evidence related to information security events? | D99: No | H99: No forensic evidence collection and preservation procedures exist. | I99: =IF($D99="Yes", 1, "") | J99: =IF($D99="No", 1, "") -> 1 | K99: =IF($D99="Not Applicable", 1, "") | L99: =IF($D99="Refer to comments", 1, "") | M99: =IF($D99="Clarification required", 1, "")
A100: 1 | B100: 5.29 | C100: Does the organization determine its requirements for adapting information security controls during disruption? | D100: No | H100: Requirements for adapting security controls during disruption (e.g. regional office outages) have not been determined. | I100: =IF($D100="Yes", 1, "") | J100: =IF($D100="No", 1, "") -> 1 | K100: =IF($D100="Not Applicable", 1, "") | L100: =IF($D100="Refer to comments", 1, "") | M100: =IF($D100="Clarification required", 1, "")
A101: 1 | B101: 5.30a | C101: Has ICT readiness been planned, implemented, maintained and tested based on business continuity objectives and ICT continuity requirements? | D101: No | H101: ICT readiness for business continuity has not been planned, implemented or tested. | I101: =IF($D101="Yes", 1, "") | J101: =IF($D101="No", 1, "") -> 1 | K101: =IF($D101="Not Applicable", 1, "") | L101: =IF($D101="Refer to comments", 1, "") | M101: =IF($D101="Clarification required", 1, "")
A102: 1 | B102: 5.30b | C102: Has the organization conducted a Business Impact Analysis (BIA) to determine ICT continuity requirements? | D102: No | H102: No Business Impact Analysis has been conducted. | I102: =IF($D102="Yes", 1, "") | J102: =IF($D102="No", 1, "") -> 1 | K102: =IF($D102="Not Applicable", 1, "") | L102: =IF($D102="Refer to comments", 1, "") | M102: =IF($D102="Clarification required", 1, "")
A103: 1 | B103: 5.31 | C103: Have legal, statutory, regulatory and contractual requirements relevant to information security been identified, documented and are they kept up to date? | D103: Refer to comments | H103: Legal and regulatory requirements relevant to freight, customs and cross-border trade are tracked by the compliance/legal function, but information-security-specific legal and contractual requirements (e.g. GDPR for EU-linked shipments) have not been separately catalogued. | I103: =IF($D103="Yes", 1, "") | J103: =IF($D103="No", 1, "") | K103: =IF($D103="Not Applicable", 1, "") | L103: =IF($D103="Refer to comments", 1, "") -> 1 | M103: =IF($D103="Clarification required", 1, "")
A104: 1 | B104: 5.32 | C104: Has the organization implemented appropriate procedures to protect intellectual property rights? | D104: No | H104: No specific procedures exist to protect intellectual property rights beyond standard contractual clauses. | I104: =IF($D104="Yes", 1, "") | J104: =IF($D104="No", 1, "") -> 1 | K104: =IF($D104="Not Applicable", 1, "") | L104: =IF($D104="Refer to comments", 1, "") | M104: =IF($D104="Clarification required", 1, "")
A105: 1 | B105: 5.33a | C105: Does the organization protect records from loss, destruction, falsification, unauthorized access and unauthorized release? | D105: Refer to comments | H105: Shipment and customer records are stored in the cloud tracking platform and on-premise WMS with basic system access controls, but no formal records-protection procedures exist. | I105: =IF($D105="Yes", 1, "") | J105: =IF($D105="No", 1, "") | K105: =IF($D105="Not Applicable", 1, "") | L105: =IF($D105="Refer to comments", 1, "") -> 1 | M105: =IF($D105="Clarification required", 1, "")
A106: 1 | B106: 5.33b | C106: Does the organization use data storage systems that allow records to be retrieved in an acceptable time frame and format? | D106: Yes | H106: Both the cloud tracking platform and WMS allow records to be retrieved within an acceptable timeframe to support day-to-day freight operations. | I106: =IF($D106="Yes", 1, "") -> 1 | J106: =IF($D106="No", 1, "") | K106: =IF($D106="Not Applicable", 1, "") | L106: =IF($D106="Refer to comments", 1, "") | M106: =IF($D106="Clarification required", 1, "")
A107: 1 | B107: 5.34a | C107: Has the organization identified and met the requirements regarding the preservation of privacy and protection of PII according to applicable laws and regulations and contractual requirements? | D107: No | H107: PII protection requirements (including GDPR for shipments touching EU customers) have not been formally identified and mapped to controls. | I107: =IF($D107="Yes", 1, "") | J107: =IF($D107="No", 1, "") -> 1 | K107: =IF($D107="Not Applicable", 1, "") | L107: =IF($D107="Refer to comments", 1, "") | M107: =IF($D107="Clarification required", 1, "")
A108: 1 | B108: 5.34b | C108: Has the organization established and communicated a topic-specific policy on privacy and protection of PII to all relevant interested parties? | D108: No | H108: No topic-specific privacy/PII policy has been established or communicated. | I108: =IF($D108="Yes", 1, "") | J108: =IF($D108="No", 1, "") -> 1 | K108: =IF($D108="Not Applicable", 1, "") | L108: =IF($D108="Refer to comments", 1, "") | M108: =IF($D108="Clarification required", 1, "")
A109: 1 | B109: 5.35 | C109: Does the organization have processes in place to conduct independent reviews? | D109: No | H109: No independent review process for information security exists. | I109: =IF($D109="Yes", 1, "") | J109: =IF($D109="No", 1, "") -> 1 | K109: =IF($D109="Not Applicable", 1, "") | L109: =IF($D109="Refer to comments", 1, "") | M109: =IF($D109="Clarification required", 1, "")
A110: 1 | B110: 5.36 | C110: Does the organization have a process for how to review that information security requirements defined in the information security policy, topic-specific policies, rules, standards and other applicable regulations are met? | D110: No | H110: No process exists to review conformance with security requirements, as no policy suite currently exists to review against. | I110: =IF($D110="Yes", 1, "") | J110: =IF($D110="No", 1, "") -> 1 | K110: =IF($D110="Not Applicable", 1, "") | L110: =IF($D110="Refer to comments", 1, "") | M110: =IF($D110="Clarification required", 1, "")
A111: 1 | B111: 5.37 | C111: Are operating procedures for information processing facilities documented and made available to personnel who need them? | D111: No | H111: Operating procedures for information processing facilities (WMS, tracking platform, servers) are not formally documented. | I111: =IF($D111="Yes", 1, "") | J111: =IF($D111="No", 1, "") -> 1 | K111: =IF($D111="Not Applicable", 1, "") | L111: =IF($D111="Refer to comments", 1, "") | M111: =IF($D111="Clarification required", 1, "")
B112: 6 - PEOPLE CONTROLS | D112: Select your response from the dropdown box. | E112: Enter the details of the Policy related to this requirement (if applicable) | F112: Enter the details of the any other document related to this requirement (if applicable) | G112: Enter the document(s) reference details or a link to the document | H112: Add comments or enter a customised response here. | I112: Yes | J112: No | K112: NA | L112: Refer to comments | M112: Clarification required
A113: 1 | B113: 6.1a | C113: Are background verification checks carried out prior personnel to joining the organization? | D113: Yes | H113: Standard pre-employment background and reference checks are carried out by HR for new hires, including warehouse and driver personnel. | I113: =IF($D113="Yes", 1, "") -> 1 | J113: =IF($D113="No", 1, "") | K113: =IF($D113="Not Applicable", 1, "") | L113: =IF($D113="Refer to comments", 1, "") | M113: =IF($D113="Clarification required", 1, "")
A114: 1 | B114: 6.1b | C114: Are background verification checks carried out on an ongoing basis to take into consideration applicable laws, regulations and ethics? | D114: No | H114: Background checks are only performed at hiring; there is no ongoing re-verification process. | I114: =IF($D114="Yes", 1, "") | J114: =IF($D114="No", 1, "") -> 1 | K114: =IF($D114="Not Applicable", 1, "") | L114: =IF($D114="Refer to comments", 1, "") | M114: =IF($D114="Clarification required", 1, "")
A115: 1 | B115: 6.1c | C115: Are background verification checks proportional to the business requirements, the classification of the information to be accessed and the perceived risks? | D115: Refer to comments | H115: Background checks are applied fairly consistently but are not formally scaled to the classification of information a role can access, since no classification scheme exists. | I115: =IF($D115="Yes", 1, "") | J115: =IF($D115="No", 1, "") | K115: =IF($D115="Not Applicable", 1, "") | L115: =IF($D115="Refer to comments", 1, "") -> 1 | M115: =IF($D115="Clarification required", 1, "")
A116: 1 | B116: 6.2 | C116: Do employment contracts state the personnel's and organization's responsibilities for information security? | D116: Refer to comments | H116: Standard employment contracts include general confidentiality clauses, but do not yet include specific information security responsibilities. | I116: =IF($D116="Yes", 1, "") | J116: =IF($D116="No", 1, "") | K116: =IF($D116="Not Applicable", 1, "") | L116: =IF($D116="Refer to comments", 1, "") -> 1 | M116: =IF($D116="Clarification required", 1, "")
A117: 1 | B117: 6.3a | C117: Do personnel and relevant interested parties receive appropriate information security awareness, education and training? | D117: No | H117: No formal information security awareness, education or training programme has been rolled out to personnel. | I117: =IF($D117="Yes", 1, "") | J117: =IF($D117="No", 1, "") -> 1 | K117: =IF($D117="Not Applicable", 1, "") | L117: =IF($D117="Refer to comments", 1, "") | M117: =IF($D117="Clarification required", 1, "")
...

Sheet Clarification
B1: ISO/IEC 27001:2022 Information Security Management System (ISMS) GAP ANALYSIS QUESTIONNAIRE - Clarification required Falcon Freight Solutions
B3: Ref | C3: Question | D3: Clarification question | E3: Response
B4: ISO/IEC 27001:2022 Clauses Gap Analysis Questionnaire - Clarification | E4: Question numbers highlighted in blue indicate that clarification is required and a clarification question needs to be asked.
B5: Clause 4 - Context of the Organization | F5: Hidden
A6: 1 | B6: 4.1a | C6: Has the organization determined external and internal issues that are relevant to and affect the ISMS' ability to achieve its intended outcomes? | F6: =COUNTIF(D6, "*") -> 0 | G6: =COUNTIF('ISO27k Gap Analysis Questions'!M10, "1") -> 0
A7: 1 | B7: 4.2a | C7: Has the organization identified interested parties relevant to the ISMS, their relevant requirements and which of these will be addressed by the ISMS? | F7: =COUNTIF(D7, "*") -> 0 | G7: =COUNTIF('ISO27k Gap Analysis Questions'!M11, "1") -> 0
A8: 1 | B8: 4.3a | C8: Has the organization determined the scope of its ISMS? | F8: =COUNTIF(D8, "*") -> 0 | G8: =COUNTIF('ISO27k Gap Analysis Questions'!M12, "1") -> 0
A9: 1 | B9: 4.4a | C9: Has the organization established, implemented, maintained, and continually improves an ISMS in accordance with the requirements of ISO/IEC 27001:2022? | F9: =COUNTIF(D9, "*") -> 0 | G9: =COUNTIF('ISO27k Gap Analysis Questions'!M13, "1") -> 0
B10: Clause 5 - Leadership
A11: 1 | B11: 5.1a | C11: Are the objectives of the ISMS compatible with the organization's strategic direction and mission? | F11: =COUNTIF(D11, "*") -> 0 | G11: =COUNTIF('ISO27k Gap Analysis Questions'!M15, "1") -> 0
A12: 1 | B12: 5.2a | C12: Is an Information Security Policy available and appropriate to the purpose and context of the organization and does it support the strategic direction of the company? | F12: =COUNTIF(D12, "*") -> 0 | G12: =COUNTIF('ISO27k Gap Analysis Questions'!M16, "1") -> 0
A13: 1 | B13: 5.3a | C13: Has the organization's top management established (and are they supportive of,) a mechanism for communicating responsibilities and authorities for roles relevant to information security within the organization? | F13: =COUNTIF(D13, "*") -> 0 | G13: =COUNTIF('ISO27k Gap Analysis Questions'!M17, "1") -> 0
B14: Clause 6 - Planning
A15: 1 | B15: 6.1a | C15: Has organization defined and applied an information security risk assessment process? | F15: =COUNTIF(D15, "*") -> 0 | G15: =COUNTIF('ISO27k Gap Analysis Questions'!M19, "1") -> 0
A16: 1 | B16: 6.1b | C16: Does the organization have a documented risk treatment process? | F16: =COUNTIF(D16, "*") -> 0 | G16: =COUNTIF('ISO27k Gap Analysis Questions'!M20, "1") -> 0
A17: 1 | B17: 6.1c | C17: Has the organization produced a Statement of Applicability (SoA)? | F17: =COUNTIF(D17, "*") -> 0 | G17: =COUNTIF('ISO27k Gap Analysis Questions'!M21, "1") -> 0
A18: 1 | B18: 6.2a | C18: Has the organization established information security objectives at applicable functions and levels within the business and are they consistent with the Information Security Policy? | F18: =COUNTIF(D18, "*") -> 0 | G18: =COUNTIF('ISO27k Gap Analysis Questions'!M22, "1") -> 0
A19: 1 | B19: 6.3a | C19: When the organization determines the need for changes to the information security management system, are the changes carried out in a planned manner? | F19: =COUNTIF(D19, "*") -> 0 | G19: =COUNTIF('ISO27k Gap Analysis Questions'!M23, "1") -> 0
B20: Clause 7 - Support
A21: 1 | B21: 7.1a | C21: Has the organization determined and does it provide the resources needed for the establishment, implementation, maintenance, and continual improvement of the ISMS? | F21: =COUNTIF(D21, "*") -> 0 | G21: =COUNTIF('ISO27k Gap Analysis Questions'!M25, "1") -> 0
A22: 1 | B22: 7.2a | C22: Has the organization determined the necessary competence of person(s) doing work under its control that affects its information security performance? | F22: =COUNTIF(D22, "*") -> 0 | G22: =COUNTIF('ISO27k Gap Analysis Questions'!M26, "1") -> 0
A23: 1 | B23: 7.3a | C23: Are the organizations employees made aware of the Information Security Policy? | F23: =COUNTIF(D23, "*") -> 0 | G23: =COUNTIF('ISO27k Gap Analysis Questions'!M27, "1") -> 0
A24: 1 | B24: 7.4a | C24: Has the organization determined the need for internal and external communications relevant to the ISMS? | F24: =COUNTIF(D24, "*") -> 0 | G24: =COUNTIF('ISO27k Gap Analysis Questions'!M28, "1") -> 0
A25: 1 | B25: 7.5a | C25: Does the organization's ISMS include documented information as required by ISO/IEC 27001:2022? | F25: =COUNTIF(D25, "*") -> 0 | G25: =COUNTIF('ISO27k Gap Analysis Questions'!M29, "1") -> 0
A26: 1 | B26: 7.5b | C26: Is documented information required by the ISMS and by ISO/IEC 27001:2022 controlled? | F26: =COUNTIF(D26, "*") -> 0 | G26: =COUNTIF('ISO27k Gap Analysis Questions'!M30, "1") -> 0
B27: Clause 8 - Operation
A28: 1 | B28: 8.1a | C28: Has the organization planned, implemented and does it control the processes needed to meet requirements, and to implement the actions determined in Clause 6 (Planning)? | F28: =COUNTIF(D28, "*") -> 0 | G28: =COUNTIF('ISO27k Gap Analysis Questions'!M32, "1") -> 0
A29: 1 | B29: 8.2a | C29: Does the organization perform information security risk assessments at planned intervals or when significant changes are proposed or occur? | F29: =COUNTIF(D29, "*") -> 0 | G29: =COUNTIF('ISO27k Gap Analysis Questions'!M33, "1") -> 0
A30: 1 | B30: 8.3a | C30: Has the organization implemented an information security risk treatment plan? | F30: =COUNTIF(D30, "*") -> 0 | G30: =COUNTIF('ISO27k Gap Analysis Questions'!M34, "1") -> 0
B31: Clause 9 - Performance evaluation
A32: 1 | B32: 9.1a | C32: Has the organization determined what needs to monitored and measured, including information security processes and controls? | F32: =COUNTIF(D32, "*") -> 0 | G32: =COUNTIF('ISO27k Gap Analysis Questions'!M36, "1") -> 0
A33: 1 | B33: 9.2a | C33: Does the organization conduct internal audits of their ISMS at planned intervals? | F33: =COUNTIF(D33, "*") -> 0 | G33: =COUNTIF('ISO27k Gap Analysis Questions'!M37, "1") -> 0
A34: 1 | B34: 9.2b | C34: Has the organization planned, established, implemented and does it maintain an audit programme(s), including the frequency, methods, responsibilities, planning requirements and reporting? | F34: =COUNTIF(D34, "*") -> 0 | G34: =COUNTIF('ISO27k Gap Analysis Questions'!M38, "1") -> 0
A35: 1 | B35: 9.3a | C35: Does the organizations top management review the organization's ISMS at planned intervals to ensure its continuing suitability, adequacy and effectiveness? | F35: =COUNTIF(D35, "*") -> 0 | G35: =COUNTIF('ISO27k Gap Analysis Questions'!M39, "1") -> 0
A36: 1 | B36: 9.3b | C36: Do the results of management reviews include decisions related to continual improvement opportunities and any needs for changes to the ISMS? | F36: =COUNTIF(D36, "*") -> 0 | G36: =COUNTIF('ISO27k Gap Analysis Questions'!M40, "1") -> 0
B37: Clause 10 - Improvement
A38: 1 | B38: 10.1a | C38: Does the organization continually improve the suitability, adequacy, and effectiveness of their ISMS? | F38: =COUNTIF(D38, "*") -> 0 | G38: =COUNTIF('ISO27k Gap Analysis Questions'!M42, "1") -> 0
A39: 1 | B39: 10.2a | C39: When a nonconformity occurs, does the organization react to the nonconformity, and as applicable take action to control and correct it? | F39: =COUNTIF(D39, "*") -> 0 | G39: =COUNTIF('ISO27k Gap Analysis Questions'!M43, "1") -> 0
B40: ISO/IEC 27001:2022 Annex A Gap Analysis Questionnaire - Clarification
B41: 5 - ORGANIZATIONAL CONTROLS
A42: 1 | B42: 5.1a | C42: Has an Information Security policy and topic-specific policies been defined, approved by management and published? | F42: =COUNTIF(D42, "*") -> 0 | G42: =COUNTIF('ISO27k Gap Analysis Questions'!M46, "1") -> 0
A43: 1 | B43: 5.1b | C43: Has the Information Security policy and topic-specific policies been communicated to and acknowledged by relevant personnel and relevant interested parties? | F43: =COUNTIF(D43, "*") -> 0 | G43: =COUNTIF('ISO27k Gap Analysis Questions'!M47, "1") -> 0
A44: 1 | B44: 5.1c | C44: Are the Information Security policy and topic-specific policies reviewed at planned intervals and if significant changes occur? | F44: =COUNTIF(D44, "*") -> 0 | G44: =COUNTIF('ISO27k Gap Analysis Questions'!M48, "1") -> 0
A45: 1 | B45: 5.2 | C45: Have Information Security roles and responsibilities been defined and allocated according to organizational needs? | F45: =COUNTIF(D45, "*") -> 0 | G45: =COUNTIF('ISO27k Gap Analysis Questions'!M49, "1") -> 0
A46: 1 | B46: 5.3 | C46: Are conflicting duties and conflicting areas of responsibility segregated? | F46: =COUNTIF(D46, "*") -> 0 | G46: =COUNTIF('ISO27k Gap Analysis Questions'!M50, "1") -> 0
A47: 1 | B47: 5.4 | C47: Does management ensure that all personnel to apply Information Security in accordance with the established Information Security policy, topic-specific policies and procedures of the organization? | F47: =COUNTIF(D47, "*") -> 0 | G47: =COUNTIF('ISO27k Gap Analysis Questions'!M51, "1") -> 0
A48: 1 | B48: 5.5 | C48: Does the organization maintain contact with relevant authorities? | F48: =COUNTIF(D48, "*") -> 0 | G48: =COUNTIF('ISO27k Gap Analysis Questions'!M52, "1") -> 0
A49: 1 | B49: 5.6 | C49: Does the organization maintain contact with special interest groups or other specialist security forums and professional associations? | F49: =COUNTIF(D49, "*") -> 0 | G49: =COUNTIF('ISO27k Gap Analysis Questions'!M53, "1") -> 0
A50: 1 | B50: 5.7a | C50: Is information relating to information security threats collected and analysed to produce threat intelligence? | F50: =COUNTIF(D50, "*") -> 0 | G50: =COUNTIF('ISO27k Gap Analysis Questions'!M54, "1") -> 0
A51: 1 | B51: 5.7b | C51: Does the organization categorize threats at the strategic, tactical and operational levels? | F51: =COUNTIF(D51, "*") -> 0 | G51: =COUNTIF('ISO27k Gap Analysis Questions'!M55, "1") -> 0
A52: 1 | B52: 5.7c | C52: Does the organization share threat intelligence with other organizations on a mutual basis in order to improve overall threat intelligence? | F52: =COUNTIF(D52, "*") -> 0 | G52: =COUNTIF('ISO27k Gap Analysis Questions'!M56, "1") -> 0
A53: 1 | B53: 5.8a | C53: Does the organization integrate information security into project management? | F53: =COUNTIF(D53, "*") -> 0 | G53: =COUNTIF('ISO27k Gap Analysis Questions'!M57, "1") -> 0
A54: 1 | B54: 5.8b | C54: Are information security risks assessed and treated at an early stage and periodically as part of project risks throughout the project life cycle? | F54: =COUNTIF(D54, "*") -> 0 | G54: =COUNTIF('ISO27k Gap Analysis Questions'!M58, "1") -> 0
A55: 1 | B55: 5.8c | C55: Are information security requirements determined for all types of projects? | F55: =COUNTIF(D55, "*") -> 0 | G55: =COUNTIF('ISO27k Gap Analysis Questions'!M59, "1") -> 0
A56: 1 | B56: 5.9a | C56: Has an inventory of information and other associated assets, including owners, been developed and maintained? | F56: =COUNTIF(D56, "*") -> 0 | G56: =COUNTIF('ISO27k Gap Analysis Questions'!M60, "1") -> 0
A57: 1 | B57: 5.9b | C57: Is the inventory of information and other associated assets accurate, up to date, consistent and aligned with other inventories? | F57: =COUNTIF(D57, "*") -> 0 | G57: =COUNTIF('ISO27k Gap Analysis Questions'!M61, "1") -> 0
A58: 1 | B58: 5.9c | C58: Is the location of assets included in the inventory? | F58: =COUNTIF(D58, "*") -> 0 | G58: =COUNTIF('ISO27k Gap Analysis Questions'!M62, "1") -> 0
A59: 1 | B59: 5.9d | C59: Are assets classified in accordance with the organizations classification scheme? | F59: =COUNTIF(D59, "*") -> 0 | G59: =COUNTIF('ISO27k Gap Analysis Questions'!M63, "1") -> 0
A60: 1 | B60: 5.9e | C60: Is ownership of assets assigned when the assets are created or when assets are transferred? | F60: =COUNTIF(D60, "*") -> 0 | G60: =COUNTIF('ISO27k Gap Analysis Questions'!M64, "1") -> 0
A61: 1 | B61: 5.9f | C61: Is asset ownership reassigned when asset owners leave or change job roles? | F61: =COUNTIF(D61, "*") -> 0 | G61: =COUNTIF('ISO27k Gap Analysis Questions'!M65, "1") -> 0
... A76: 1 | B76: 5.15b | C76: Has the organization established and implemented a topic specific policy for access control? | F76: =COUNTIF(D76, "*") -> 0 | G76: =COUNTIF('ISO27k Gap Analysis Questions'!M80, "1") -> 0
A77: 1 | B77: 5.16 | C77: Does the organization manage the full life cycle of identities? | F77: =COUNTIF(D77, "*") -> 0 | G77: =COUNTIF('ISO27k Gap Analysis Questions'!M81, "1") -> 0
A78: 1 | B78: 5.17a | C78: Is the allocation and management of authentication information controlled by a management process? | F78: =COUNTIF(D78, "*") -> 0 | G78: =COUNTIF('ISO27k Gap Analysis Questions'!M82, "1") -> 0
A79: 1 | B79: 5.17b | C79: Does the allocation and management of authentication information include advising personnel on the appropriate handling of authentication information? | F79: =COUNTIF(D79, "*") -> 0 | G79: =COUNTIF('ISO27k Gap Analysis Questions'!M83, "1") -> 0
A80: 1 | B80: 5.17c | C80: Are personnel who have access to or use authentication advised on their responsibilities? | F80: =COUNTIF(D80, "*") -> 0 | G80: =COUNTIF('ISO27k Gap Analysis Questions'!M84, "1") -> 0
A81: 1 | B81: 5.17d | C81: Does the organization have a password management system in place? | F81: =COUNTIF(D81, "*") -> 0 | G81: =COUNTIF('ISO27k Gap Analysis Questions'!M85, "1") -> 0
A82: 1 | B82: 5.18a | C82: Are access rights to information and other associated assets provisioned, reviewed, modified and removed in accordance with the organization’s topic-specific policy on and rules for access control? | F82: =COUNTIF(D82, "*") -> 0 | G82: =COUNTIF('ISO27k Gap Analysis Questions'!M86, "1") -> 0
A83: 1 | B83: 5.18b | C83: Does the organization have a process for the review of access rights? | F83: =COUNTIF(D83, "*") -> 0 | G83: =COUNTIF('ISO27k Gap Analysis Questions'!M87, "1") -> 0
A84: 1 | B84: 5.19 | C84: Have processes and procedures been defined and implemented to manage the information security risks associated with the use of supplier’s products or services? | F84: =COUNTIF(D84, "*") -> 0 | G84: =COUNTIF('ISO27k Gap Analysis Questions'!M88, "1") -> 0
A85: 1 | B85: 5.2 | C85: Have the relevant information security requirements been established and agreed with each supplier based on the type of supplier relationship? | F85: =COUNTIF(D85, "*") -> 0 | G85: =COUNTIF('ISO27k Gap Analysis Questions'!M89, "1") -> 0
A86: 1 | B86: 5.21 | C86: Have processes and procedures been defined and implemented to manage the information security risks associated with the ICT products and services supply chain? | F86: =COUNTIF(D86, "*") -> 0 | G86: =COUNTIF('ISO27k Gap Analysis Questions'!M90, "1") -> 0
A87: 1 | B87: 5.22 | C87: Does the organization regularly monitor, review, evaluate and manage change in supplier information security practices and service delivery? | F87: =COUNTIF(D87, "*") -> 0 | G87: =COUNTIF('ISO27k Gap Analysis Questions'!M91, "1") -> 0
A88: 1 | B88: 5.23a | C88: Have processes for acquisition, use, management and exit from cloud services been established in accordance with the organization’s information security requirements? | F88: =COUNTIF(D88, "*") -> 0 | G88: =COUNTIF('ISO27k Gap Analysis Questions'!M92, "1") -> 0
A89: 1 | B89: 5.23b | C89: Has the organization established and communicated topic-specific policy on the use of cloud services to all relevant interested parties? | F89: =COUNTIF(D89, "*") -> 0 | G89: =COUNTIF('ISO27k Gap Analysis Questions'!M93, "1") -> 0
A90: 1 | B90: 5.24a | C90: Has the organization established appropriate information security incident management processes? | F90: =COUNTIF(D90, "*") -> 0 | G90: =COUNTIF('ISO27k Gap Analysis Questions'!M94, "1") -> 0
A91: 1 | B91: 5.24b | C91: Has the organization defined roles and responsibilities for the information security incident management process? | F91: =COUNTIF(D91, "*") -> 0 | G91: =COUNTIF('ISO27k Gap Analysis Questions'!M95, "1") -> 0
A92: 1 | B92: 5.25 | C92: Does the organization have a categorization and prioritization scheme of information security incidents? | F92: =COUNTIF(D92, "*") -> 0 | G92: =COUNTIF('ISO27k Gap Analysis Questions'!M96, "1") -> 0
A93: 1 | B93: 5.26 | C93: Are information security incidents responded to in accordance with documented procedures? | F93: =COUNTIF(D93, "*") -> 0 | G93: =COUNTIF('ISO27k Gap Analysis Questions'!M97, "1") -> 0
A94: 1 | B94: 5.27 | C94: Has the organization established procedures to quantify and monitor the types, volumes and costs of information security incidents? | F94: =COUNTIF(D94, "*") -> 0 | G94: =COUNTIF('ISO27k Gap Analysis Questions'!M98, "1") -> 0
A95: 1 | B95: 5.28 | C95: Has the organization established and implemented procedures for the identification, collection, acquisition and preservation of evidence related to information security events? | F95: =COUNTIF(D95, "*") -> 0 | G95: =COUNTIF('ISO27k Gap Analysis Questions'!M99, "1") -> 0
A96: 1 | B96: 5.29 | C96: Does the organization determine its requirements for adapting information security controls during disruption? | F96: =COUNTIF(D96, "*") -> 0 | G96: =COUNTIF('ISO27k Gap Analysis Questions'!M100, "1") -> 0
A97: 1 | B97: 5.30a | C97: Has ICT readiness been planned, implemented, maintained and tested based on business continuity objectives and ICT continuity requirements? | F97: =COUNTIF(D97, "*") -> 0 | G97: =COUNTIF('ISO27k Gap Analysis Questions'!M101, "1") -> 0
A98: 1 | B98: 5.30b | C98: Has the organization conducted a Business Impact Analysis (BIA) to determine ICT continuity requirements? | F98: =COUNTIF(D98, "*") -> 0 | G98: =COUNTIF('ISO27k Gap Analysis Questions'!M102, "1") -> 0
A99: 1 | B99: 5.31 | C99: Have legal, statutory, regulatory and contractual requirements relevant to information security been identified, documented and are they kept up to date? | F99: =COUNTIF(D99, "*") -> 0 | G99: =COUNTIF('ISO27k Gap Analysis Questions'!M103, "1") -> 0
A100: 1 | B100: 5.32 | C100: Has the organization implemented appropriate procedures to protect intellectual property rights? | F100: =COUNTIF(D100, "*") -> 0 | G100: =COUNTIF('ISO27k Gap Analysis Questions'!M104, "1") -> 0
A101: 1 | B101: 5.33a | C101: Does the organization protect records from loss, destruction, falsification, unauthorized access and unauthorized release? | F101: =COUNTIF(D101, "*") -> 0 | G101: =COUNTIF('ISO27k Gap Analysis Questions'!M105, "1") -> 0
A102: 1 | B102: 5.33b | C102: Does the organization use data storage systems that allow records to be retrieved in an acceptable time frame and format? | F102: =COUNTIF(D102, "*") -> 0 | G102: =COUNTIF('ISO27k Gap Analysis Questions'!M106, "1") -> 0
A103: 1 | B103: 5.34a | C103: Has the organization identified and met the requirements regarding the preservation of privacy and protection of PII according to applicable laws and regulations and contractual requirements? | F103: =COUNTIF(D103, "*") -> 0 | G103: =COUNTIF('ISO27k Gap Analysis Questions'!M107, "1") -> 0
A104: 1 | B104: 5.34b | C104: Has the organization established and communicated a topic-specific policy on privacy and protection of PII to all relevant interested parties? | F104: =COUNTIF(D104, "*") -> 0 | G104: =COUNTIF('ISO27k Gap Analysis Questions'!M108, "1") -> 0
A105: 1 | B105: 5.35 | C105: Does the organization have processes in place to conduct independent reviews? | F105: =COUNTIF(D105, "*") -> 0 | G105: =COUNTIF('ISO27k Gap Analysis Questions'!M109, "1") -> 0
A106: 1 | B106: 5.36 | C106: Does the organization have a process for how to review that information security requirements defined in the information security policy, topic-specific policies, rules, standards and other applicable regulations are met? | F106: =COUNTIF(D106, "*") -> 0 | G106: =COUNTIF('ISO27k Gap Analysis Questions'!M110, "1") -> 0
A107: 1 | B107: 5.37 | C107: Are operating procedures for information processing facilities documented and made available to personnel who need them? | F107: =COUNTIF(D107, "*") -> 0 | G107: =COUNTIF('ISO27k Gap Analysis Questions'!M111, "1") -> 0
B108: 6 - PEOPLE CONTROLS
A109: 1 | B109: 6.1a | C109: Are background verification checks carried out prior personnel to joining the organization? | F109: =COUNTIF(D109, "*") -> 0 | G109: =COUNTIF('ISO27k Gap Analysis Questions'!M113, "1") -> 0
A110: 1 | B110: 6.1b | C110: Are background verification checks carried out on an ongoing basis to take into consideration applicable laws, regulations and ethics? | F110: =COUNTIF(D110, "*") -> 0 | G110: =COUNTIF('ISO27k Gap Analysis Questions'!M114, "1") -> 0
A111: 1 | B111: 6.1c | C111: Are background verification checks proportional to the business requirements, the classification of the information to be accessed and the perceived risks? | F111: =COUNTIF(D111, "*") -> 0 | G111: =COUNTIF('ISO27k Gap Analysis Questions'!M115, "1") -> 0
A112: 1 | B112: 6.2 | C112: Do employment contracts state the personnel's and organization's responsibilities for information security? | F112: =COUNTIF(D112, "*") -> 0 | G112: =COUNTIF('ISO27k Gap Analysis Questions'!M116, "1") -> 0
A113: 1 | B113: 6.3a | C113: Do personnel and relevant interested parties receive appropriate information security awareness, education and training? | F113: =COUNTIF(D113, "*") -> 0 | G113: =COUNTIF('ISO27k Gap Analysis Questions'!M117, "1") -> 0
A114: 1 | B114: 6.3b | C114: Do personnel and relevant interested parties receive regular updates of the organization's information security policy, topic-specific policies and procedures, as relevant for their job function? | F114: =COUNTIF(D114, "*") -> 0 | G114: =COUNTIF('ISO27k Gap Analysis Questions'!M118, "1") -> 0
A115: 1 | B115: 6.4a | C115: Does the organization have a formalized disciplinary policy? | F115: =COUNTIF(D115, "*") -> 0 | G115: =COUNTIF('ISO27k Gap Analysis Questions'!M119, "1") -> 0
...
